onepassword_keyring/__init__.py
onepassword_keyring-0.1.1.dist-info/LICENSE.md
onepassword_keyring-0.1.1.dist-info/METADATA
onepassword_keyring-0.1.1.dist-info/WHEEL
onepassword_keyring-0.1.1.dist-info/entry_points.txt
onepassword_keyring-0.1.1.dist-info/top_level.txt
onepassword_keyring-0.1.1.dist-info/zip-safe
onepassword_keyring-0.1.1.dist-info/RECORD
