Metadata-Version: 2.1
Name: onepassword-keyring
Version: 0.1.1
Summary: Keyring backend reading password data from 1Password
Home-page: https://github.com/falling-springs/onepassword-keyring
Author: Falling Springs
Author-email: fallstosprings@gmail.com
License: MIT License
Keywords: onepassword keyring password
Classifier: Development Status :: 3 - Alpha
Classifier: Intended Audience :: Developers
Classifier: License :: OSI Approved :: MIT License
Classifier: Programming Language :: Python :: 3
License-File: LICENSE.md
Requires-Dist: keyring
Provides-Extra: dev
Requires-Dist: flake8 ; extra == 'dev'
Requires-Dist: isort ; extra == 'dev'
Requires-Dist: black ; extra == 'dev'
Requires-Dist: pytest ; extra == 'dev'
Requires-Dist: pytest-mock ; extra == 'dev'
Requires-Dist: pytest-cov ; extra == 'dev'
